pysolya/__init__.py
pysolya/base58.py
pysolya/config.py
pysolya/core.py
pysolya/denomination.py
pysolya/ed25519.py
pysolya/eddsa.py
pysolya/rpc.py
pysolya/wallet.py
pysolya-0.2.1.dist-info/METADATA
pysolya-0.2.1.dist-info/WHEEL
pysolya-0.2.1.dist-info/licenses/LICENSE
pysolya-0.2.1.dist-info/RECORD
