Metadata-Version: 2.3
Name: pysolya
Version: 0.2.1
Summary: pysolya: solana blockchain sdk for humans
Project-URL: homepage, https://github.com/mohanson/pysolya
Author-email: Mohanson <mohanson@outlook.com>
License: MIT License
Requires-Dist: requests
